jsonid/__init__.py
jsonid/analysis.py
jsonid/base_obj_presets.py
jsonid/compressionlib.py
jsonid/export.py
jsonid/export_helpers.py
jsonid/file_processing.py
jsonid/helpers.py
jsonid/htm_template.py
jsonid/jsonid.py
jsonid/lookup.py
jsonid/output.py
jsonid/pronom.py
jsonid/registry.py
jsonid/registry_class.py
jsonid/registry_data.py
jsonid/registry_matchers.py
jsonid/version.py
jsonid-0.12.3.dist-info/licenses/LICENSE
utils/json2json.py
utils/jsonid2pronom.py
jsonid-0.12.3.dist-info/METADATA
jsonid-0.12.3.dist-info/WHEEL
jsonid-0.12.3.dist-info/entry_points.txt
jsonid-0.12.3.dist-info/top_level.txt
jsonid-0.12.3.dist-info/RECORD
