Metadata-Version: 2.4
Name: jsonid
Version: 0.12.3
Summary: jsonid a json identification tool
Author-email: "R. Spencer" <all.along.the.watchtower2001+github@gmail.com>
Maintainer-email: "R. Spencer" <all.along.the.watchtower2001+github@gmail.com>
Project-URL: Homepage, https://github.com/ffdev-info/jsonid
Project-URL: Bug Reports, https://github.com/ffdev-info/jsonid/issues/
Project-URL: Source, https://github.com/ffdev-info/jsonid/sourcecode/
Keywords: json,digipres,file-formats
Classifier: Development Status :: 4 - Beta
Classifier: Intended Audience :: Developers
Classifier: Programming Language :: Python :: 3.11
Classifier: Programming Language :: Python :: 3 :: Only
Requires-Python: >=3.11
License-File: LICENSE
Requires-Dist: ipfs-cid==1.0.0
Requires-Dist: PyYAML==6.0.3
Requires-Dist: python-magic-bin==0.4.14; sys_platform == "windows"
Requires-Dist: python-magic==0.4.27
Requires-Dist: unf==0.11.0
Dynamic: license-file
